{
  "개": [
    "그애",
    "기애",
    "개",
    "캐",
    "깨!",
    "괘!",
    "꽤!",
    "괴",
    "걔!",
    "꺠!",
    "게",
    "계!",
    "갭!",
    "갯!"
  ],
  "년": [
    "니!연!",
    "니!언!",
    "년!",
    "뇬!",
    "련!",
    "리!언!",
    "리!연!",
    "룐!"
  ],
  "놈": [
    "놈!",
    "뇸!",
    "놤!",
    "넘!",
    "럼!",
    "니!옴",
    "리!옴"
  ],
  "똥": [
    "똥!",
    "떵!",
    "뙁",
    "뚜엉",
    "뜨웡",
    "뜨엉"
  ],
  "랄": [
    "랄!",
    "랼!",
    "롤!",
    "럴!",
    "렬!",
    "룔!"
  ],
  "발": [
    "발!",
    "빨!",
    "팔!",
    "벌!",
    "뻘!",
    "펄!",
    "불!",
    "뿔!"
  ],
  "병": [
    "볍",
    "벙",
    "병",
    "뼝",
    "평",
    "븅",
    "비!엉!",
    "비!응!"
  ],
  "뻑": [
    "뻑!",
    "퍽!",
    "뻗!",
    "펃!"
  ],
  "새끼": [
    "새!끼",
    "새끼!",
    "세!끼",
    "쉐이",
    "쌔이",
    [
      [
        "새",
        "섀",
        "쉐",
        "세",
        "섹",
        "쎄",
        "쇠",
        "쇳",
        "쉣",
        "쌕",
        "쒜",
        "쒯",
        "시",
        "씨",
        "씌"
      ],
      [
        "기",
        "긔!",
        "귀!",
        "끼!",
        "키!"
      ]
    ],
    [
      [
        "색",
        "샏",
        "섇",
        "섹",
        "쇡",
        "쇧",
        "쉣",
        "쌕",
        "쒯"
      ],
      [
        "기",
        "끼",
        "이",
        "히"
      ]
    ],
    [
      [
        "색!",
        "쌕!",
        "샏!",
        "쌛!"
      ],
      [
        "기!",
        "이",
        "의",
        "히!"
      ]
    ]
  ],
  "색": [
    "색!",
    "쌕!",
    "샏!",
    "쌛!"
  ],
  "스": [
    "수",
    "슈",
    "스",
    "싀",
    "쑤",
    "쓔",
    "쓰",
    "씌"
  ],
  "시": [
    "디",
    "듸!",
    "뒤!",
    "띠!",
    "뛰!",
    "띄!",
    "슈",
    "슏!",
    "슙!",
    "쓔!",
    "시",
    "쉬!",
    "싀!",
    "식!",
    "십!",
    "싣!",
    "씨!",
    "지",
    "쥐!",
    "즤!",
    "찌!",
    "쮜!",
    "쯰!",
    "쓰!",
    "스",
    "습!",
    "슫!",
    "ㅅ"
  ],
  "십": [
    "십!",
    "씹!",
    "찝!"
  ],
  "쓰레기": [
    "수래!기!",
    "스랙",
    "스!래!기!",
    "스!레!기!",
    "스뢰!기",
    "스!렉!",
    "시!렉!",
    "시!레!기!",
    "쑤!래기",
    "쑤!렉!",
    "쑤!레!기!",
    "쓰!뢰!기!",
    "쓰!레!기!",
    "쓰!랙!",
    "쓰!렉!",
    "씨!레!기!",
    "씨!레!기!",
    "씨!렉",
    "쯔랙",
    "쯔렉",
    "쯔!레!기!",
    "찌랙",
    "찌렉",
    "찌!레!기!"
  ],
  "애비": [
    "애!비!",
    "앱!이",
    "앰비"
  ],
  "에미": [
    "에!미!",
    "엠!",
    "엠!이"
  ],
  "자식": [
    [
      [
        "자",
        "쟈",
        "짜",
        "쨔",
        "좌",
        "즈아",
        "쫘",
        "쯔아"
      ],
      [
        "식!",
        "씩!",
        "슥!",
        "쓱!",
        "쉭!",
        "쒹!"
      ]
    ]
  ],
  "좁": [
    "좁!",
    "쫍!"
  ],
  "좆": [
    "잦",
    "찾",
    "젖!",
    "좆!",
    "촞!",
    "좋",
    "쫗",
    "촣",
    "쫒",
    "좃",
    "좇",
    "쫒!",
    "족"
  ],
  "지": [
    "지",
    "쥐!",
    "즤!",
    "직!",
    "질!",
    "찌",
    "찍!",
    "찔!"
  ],
  "찐": [
    "찐!",
    "쯘!"
  ],
  "충": [
    "충+",
    [
      [
        "추",
        "취",
        "츠",
        "쭈",
        "쮜"
      ],
      [
        "응",
        "웅"
      ]
    ]
  ],
  "ㅗ": [
    "ㅗ",
    "ㅛ",
    "凸",
    "┴"
  ],
  "동어미": [
    "다",
    "습니다",
    "요",
    "해요"
  ],
  "형어미1": [
    "다",
    "습니다",
    "니다",
    "은"
  ]
}
